.gitignore
LICENSE
MANIFEST.in
README.md
setup.py
flatpak_module_tools/__init__.py
flatpak_module_tools/cli.py
flatpak_module_tools/config.py
flatpak_module_tools/config.yaml
flatpak_module_tools/container_builder.py
flatpak_module_tools/flatpak_builder.py
flatpak_module_tools/get_module_builds.py
flatpak_module_tools/installer.py
flatpak_module_tools/module_builder.py
flatpak_module_tools/module_locator.py
flatpak_module_tools/test_flatpak_builder.py
flatpak_module_tools/utils.py
flatpak_module_tools.egg-info/PKG-INFO
flatpak_module_tools.egg-info/SOURCES.txt
flatpak_module_tools.egg-info/dependency_links.txt
flatpak_module_tools.egg-info/entry_points.txt
flatpak_module_tools.egg-info/top_level.txt
flatpak_module_tools/templates/mock.cfg.j2
tests/test_flatpak_builder.py
tests/test_tree_processor.py